Metadata-Version: 2.1
Name: zipline-foreverbll
Version: 0.0.7
Summary: Zipline API to be use for Foreverbull
Home-page: UNKNOWN
Author: Henrik Nilsson
Author-email: henrik@lhjnilsson.com
License: UNKNOWN
Platform: UNKNOWN
Classifier: Programming Language :: Python :: 3.8
Classifier: Programming Language :: Python :: 3.9
License-File: LICENSE
Requires-Dist: zipline-reloaded (>=2.1.1)
Requires-Dist: foreverbull-core (>=0.0.25)
Provides-Extra: dev
Requires-Dist: pytest (<7.0.0,>=6.2.4) ; extra == 'dev'
Requires-Dist: pytest-mock (<4.0.0,>=3.6.1) ; extra == 'dev'
Requires-Dist: flake8 (<4.0.0,>=3.9.2) ; extra == 'dev'
Requires-Dist: black (<30,>=21.7b0) ; extra == 'dev'
Requires-Dist: isort (<6.0.0,>=5.9.3) ; extra == 'dev'
Requires-Dist: pytest-cov ; extra == 'dev'
Provides-Extra: docs
Requires-Dist: sphinx (<5.0.0,>=4.2.0) ; extra == 'docs'
Requires-Dist: alablaster ; extra == 'docs'
